README
setup.py
johansen/__init__.py
johansen/critical_values.py
johansen/johansen.py
johansen.egg-info/PKG-INFO
johansen.egg-info/SOURCES.txt
johansen.egg-info/dependency_links.txt
johansen.egg-info/requires.txt
johansen.egg-info/top_level.txt